qualifyzetest/__init__.py
qualifyzetest/main.py
qualifyzetest/module2/__init__.py
qualifyzetest/module2/main2.py
qualifyzetest-0.109.dist-info/METADATA
qualifyzetest-0.109.dist-info/WHEEL
qualifyzetest-0.109.dist-info/top_level.txt
qualifyzetest-0.109.dist-info/RECORD
