Metadata-Version: 2.1
Name: qualifyzetest
Version: 0.109
Summary: Library containing the personalized utils for the DWH of Qualifyze
Home-page: http://qualifyze.com
Author: Moise O. Romaniuc Demeter
Author-email: moise.romaniuc@qualifyze.com
License: MIT
Keywords: data utils dwh qualifyze
Platform: UNKNOWN
Classifier: Development Status :: 3 - Alpha
Classifier: Topic :: Utilities
Classifier: License :: OSI Approved :: BSD License
